{
    "configurations": [
        {
            "name": "Win32",
            "includePath": [
                "E:\\github\\STM32F429_BSP/**",
                "D:\\Keil_v5/**"
            ],
            "defines": [
                "_DEBUG",
                "UNICODE",
                "_UNICODE",
                "USE_HAL_DRIVER",
                "STM32F429xx",
                "__CC_ARM"
            ],
            "windowsSdkVersion": "10.0.19041.0",
            "compilerPath": "D:/Program Files (x86)/Microsoft Visual Studio/2019/Enterprise/VC/Tools/MSVC/14.29.30133/bin/Hostx64/x64/cl.exe",
            "cStandard": "c99",
            "cppStandard": "c++98",
            "intelliSenseMode": "windows-msvc-x64"
        }
    ],
    "version": 4
}